key_value/shared/__init__.py
key_value/shared/code_gen/gather.py
key_value/shared/code_gen/run.py
key_value/shared/code_gen/sleep.py
key_value/shared/constants.py
key_value/shared/errors/__init__.py
key_value/shared/errors/base.py
key_value/shared/errors/key_value.py
key_value/shared/errors/store.py
key_value/shared/errors/wrappers/__init__.py
key_value/shared/errors/wrappers/encryption.py
key_value/shared/errors/wrappers/limit_size.py
key_value/shared/errors/wrappers/read_only.py
key_value/shared/stores/wait.py
key_value/shared/type_checking/bear_spray.py
key_value/shared/utils/__init__.py
key_value/shared/utils/compound.py
key_value/shared/utils/managed_entry.py
key_value/shared/utils/sanitize.py
key_value/shared/utils/time_to_live.py
py_key_value_shared-0.2.7.dist-info/WHEEL
py_key_value_shared-0.2.7.dist-info/METADATA
py_key_value_shared-0.2.7.dist-info/RECORD
